README.rst
setup.cfg
setup.py
plenario_stream_core/__init__.py
plenario_stream_core/admin.py
plenario_stream_core/apps.py
plenario_stream_core/defaults.py
plenario_stream_core/enums.py
plenario_stream_core/models.py
plenario_stream_core/responses.py
plenario_stream_core/signals.py
plenario_stream_core/stubs.py
plenario_stream_core/urls.py
plenario_stream_core/utils.py
plenario_stream_core/views.py
plenario_stream_core.egg-info/PKG-INFO
plenario_stream_core.egg-info/SOURCES.txt
plenario_stream_core.egg-info/dependency_links.txt
plenario_stream_core.egg-info/requires.txt
plenario_stream_core.egg-info/top_level.txt