Metadata-Version: 1.2
Name: plenario-stream-core
Version: 0.0.2
Summary: Abstraction over stream management for Plenario.
Home-page: https://github.com/UrbanCCD-UChicago/plenario-stream-core
Author: Jesus Bracho
Author-email: jbracho@uchicago.edu
License: GPLv3
Keywords: plenario
Platform: UNKNOWN
Classifier: Development Status :: 3 - Alpha
Classifier: License :: OSI Approved :: GNU General Public License v3 (GPLv3)
Classifier: Programming Language :: Python :: 3.6
Requires-Python: >=3.6
